README.rst
setup.py
plugemin/__init__.py
plugemin/__main__.py
plugemin/cli.py
plugemin/input_plugins.py
plugemin/plugemin.py
plugemin.egg-info/PKG-INFO
plugemin.egg-info/SOURCES.txt
plugemin.egg-info/dependency_links.txt
plugemin.egg-info/entry_points.txt
plugemin.egg-info/requires.txt
plugemin.egg-info/top_level.txt
test/test_plugemin.py