Metadata-Version: 1.1
Name: plugemin
Version: 0.1.1
Summary: A template as a service utility...you know, for DevOps
Home-page: http://github.com/ilovetux/plugemin
Author: iovetux
Author-email: me@ilovetux.com
License: GPLv3
Keywords: template reports
Platform: UNKNOWN
Classifier: Development Status :: 4 - Beta
Classifier: Topic :: Utilities
Classifier: License :: OSI Approved :: GNU General Public License v3 (GPLv3)
